odoo9_addon_sale_double_validation-9.0.1.0.0.99.dev6-py3.6-nspkg.pth
odoo_addons/sale_double_validation/README.rst
odoo_addons/sale_double_validation/__init__.py
odoo_addons/sale_double_validation/__openerp__.py
odoo_addons/sale_double_validation/i18n/ca.po
odoo_addons/sale_double_validation/i18n/es.po
odoo_addons/sale_double_validation/i18n/sale_double_validation.pot
odoo_addons/sale_double_validation/models/__init__.py
odoo_addons/sale_double_validation/models/company.py
odoo_addons/sale_double_validation/models/sale.py
odoo_addons/sale_double_validation/static/description/icon.png
odoo_addons/sale_double_validation/tests/__init__.py
odoo_addons/sale_double_validation/tests/test_double_validation.py
odoo_addons/sale_double_validation/views/company.xml
odoo_addons/sale_double_validation/views/sale.xml
odoo9_addon_sale_double_validation-9.0.1.0.0.99.dev6.dist-info/METADATA
odoo9_addon_sale_double_validation-9.0.1.0.0.99.dev6.dist-info/WHEEL
odoo9_addon_sale_double_validation-9.0.1.0.0.99.dev6.dist-info/namespace_packages.txt
odoo9_addon_sale_double_validation-9.0.1.0.0.99.dev6.dist-info/top_level.txt
odoo9_addon_sale_double_validation-9.0.1.0.0.99.dev6.dist-info/RECORD
